LICENSE
MANIFEST.in
README.md
setup.py
bcp/__init__.py
bcp/models.py
bcp/settings.py
bcp/tests.py
bcp/urls.py
bcp/views.py
bcp/fonts/OCRA.ttf
bcp/fonts/README
bcp/templates/embed_example.html
bcp/templates/print.html
django_bcp.egg-info/PKG-INFO
django_bcp.egg-info/SOURCES.txt
django_bcp.egg-info/dependency_links.txt
django_bcp.egg-info/requires.txt
django_bcp.egg-info/top_level.txt