Metadata-Version: 1.1
Name: django-bcp
Version: 0.2.2
Summary: Barcode Printer for Django
Home-page: https://github.com/adlibre/django-bcp
Author: Andrew Cutler
Author-email: andrew@adlibre.com.au
License: BSD
Download-URL: https://github.com/adlibre/python-bureaucrat/archive/v0.2.2.tar.gz
Platform: UNKNOWN
Classifier: Development Status :: 5 - Production/Stable
Classifier: Environment :: Console
Classifier: Intended Audience :: Developers
Classifier: License :: OSI Approved :: BSD License
Classifier: Operating System :: Unix
Classifier: Programming Language :: Python
Classifier: Topic :: Utilities
